ds2stac_ingester/__init__.py
ds2stac_ingester/_version.py
ds2stac_ingester/cli.py
ds2stac_ingester/config_pgstac.py
ds2stac_ingester/ds2stac_ingester.py
DS2STAC_Ingester-1.1.0.dist-info/AUTHORS.rst
DS2STAC_Ingester-1.1.0.dist-info/LICENSE
DS2STAC_Ingester-1.1.0.dist-info/METADATA
DS2STAC_Ingester-1.1.0.dist-info/WHEEL
DS2STAC_Ingester-1.1.0.dist-info/top_level.txt
DS2STAC_Ingester-1.1.0.dist-info/RECORD
